MANIFEST.in
README.rst
setup.py
assetstoolkit/__init__.py
assetstoolkit/templatetags/__init__.py
assetstoolkit/templatetags/assetstoolkit.py
assetstoolkit/templatetags/settings.py
django_assets_toolkit.egg-info/PKG-INFO
django_assets_toolkit.egg-info/SOURCES.txt
django_assets_toolkit.egg-info/dependency_links.txt
django_assets_toolkit.egg-info/not-zip-safe
django_assets_toolkit.egg-info/requires.txt
django_assets_toolkit.egg-info/top_level.txt