Metadata-Version: 1.0
Name: django-assets-toolkit
Version: 0.1.2
Summary: A development toolkit for compiling sass and coffee script files.
Home-page: https://github.com/pypug/django-assets-toolkit
Author: Marconi Moreto
Author-email: caketoad@gmail.com
License: UNKNOWN
Platform: UNKNOWN
